config_argparse/__init__.py
config_argparse/argparse_action.py
config_argparse/config.py
config_argparse/value.py
config_argparse-0.3.3.dist-info/METADATA
config_argparse-0.3.3.dist-info/RECORD
config_argparse-0.3.3.dist-info/WHEEL
config_argparse-0.3.3.dist-info/top_level.txt
tests/__init__.py
tests/test_config.py
tests/test_config2.py
tests/test_value.py
