Metadata-Version: 2.1
Name: config-argparse
Version: 0.3.3
Summary: config library based on standard ArgumentParser
Home-page: https://github.com/cormoran/config_argparse
Author: cormoran
Author-email: cormoran707@gmail.com
License: mit
Platform: UNKNOWN
